pyxidust/__init__.py
pyxidust/arc.py
pyxidust/utils.py
pyxidust-0.1.2.dist-info/LICENSE
pyxidust-0.1.2.dist-info/METADATA
pyxidust-0.1.2.dist-info/WHEEL
pyxidust-0.1.2.dist-info/top_level.txt
pyxidust-0.1.2.dist-info/RECORD
