Metadata-Version: 2.1
Name: pyxidust
Version: 0.1.2
Summary: General-purpose library
Home-page: https://github.com/pyxidust
Author: Gabriel Peck
Author-email: pyxidust@pm.me
Classifier: Programming Language :: Python :: 3
Classifier: License :: OSI Approved :: MIT License
Classifier: Operating System :: OS Independent
Requires-Python: >=3.7
License-File: LICENSE
